assemblyline_v3_service/__init__.py
assemblyline_v3_service/run_service.py
assemblyline_v3_service/common/__init__.py
assemblyline_v3_service/common/base.py
assemblyline_v3_service/common/chunk.py
assemblyline_v3_service/common/classification.py
assemblyline_v3_service/common/classification.yml
assemblyline_v3_service/common/compat_tag_map.py
assemblyline_v3_service/common/constants.py
assemblyline_v3_service/common/context.py
assemblyline_v3_service/common/default_service_manifest.yml
assemblyline_v3_service/common/dict_utils.py
assemblyline_v3_service/common/digests.py
assemblyline_v3_service/common/entropy.py
assemblyline_v3_service/common/exceptions.py
assemblyline_v3_service/common/frequency.pyx
assemblyline_v3_service/common/heuristics.py
assemblyline_v3_service/common/hexdump.py
assemblyline_v3_service/common/identify.py
assemblyline_v3_service/common/importing.py
assemblyline_v3_service/common/install.py
assemblyline_v3_service/common/isotime.py
assemblyline_v3_service/common/log.py
assemblyline_v3_service/common/logformat.py
assemblyline_v3_service/common/mock_forge.py
assemblyline_v3_service/common/mock_modules.py
assemblyline_v3_service/common/net.py
assemblyline_v3_service/common/net_static.py
assemblyline_v3_service/common/path.py
assemblyline_v3_service/common/reaper.py
assemblyline_v3_service/common/result.py
assemblyline_v3_service/common/str_utils.py
assemblyline_v3_service/common/tagging.py
assemblyline_v3_service/common/task.py
assemblyline_v3_service/common/timeout.py
assemblyline_v3_service/common/version.py
assemblyline_v3_service/common/transport/__init__.py
assemblyline_v3_service/common/transport/base.py
assemblyline_v3_service/common/transport/local.py
assemblyline_v3_service/common/yara/YaraParser.py
assemblyline_v3_service/common/yara/YaraValidator.py
assemblyline_v3_service/common/yara/__init__.py
assemblyline_v3_service/common/yara/yara_importer.py
assemblyline_v3_service-3.3.0.dev58.dist-info/LICENCE.md
assemblyline_v3_service-3.3.0.dev58.dist-info/METADATA
assemblyline_v3_service-3.3.0.dev58.dist-info/WHEEL
assemblyline_v3_service-3.3.0.dev58.dist-info/top_level.txt
assemblyline_v3_service-3.3.0.dev58.dist-info/RECORD
